LICENSE.md
MANIFEST.in
README.md
setup.cfg
setup.py
e_fonenana_frontend.egg-info/PKG-INFO
e_fonenana_frontend.egg-info/SOURCES.txt
e_fonenana_frontend.egg-info/dependency_links.txt
e_fonenana_frontend.egg-info/not-zip-safe
e_fonenana_frontend.egg-info/requires.txt
e_fonenana_frontend.egg-info/top_level.txt
hass_frontend/00acd3c1a20453ded638.chunk.js
hass_frontend/00acd3c1a20453ded638.chunk.js.gz
hass_frontend/00acd3c1a20453ded638.chunk.js.map
hass_frontend/036fda24e538d06cc4b5.chunk.js
hass_frontend/036fda24e538d06cc4b5.chunk.js.gz
hass_frontend/036fda24e538d06cc4b5.chunk.js.map
hass_frontend/05fa1469bc354d64acee.chunk.js
hass_frontend/05fa1469bc354d64acee.chunk.js.gz
hass_frontend/05fa1469bc354d64acee.chunk.js.map
hass_frontend/079fba7781ad3dc7c7bb.chunk.js
hass_frontend/079fba7781ad3dc7c7bb.chunk.js.gz
hass_frontend/079fba7781ad3dc7c7bb.chunk.js.map
hass_frontend/08b70024d3efa1557093.chunk.js
hass_frontend/08b70024d3efa1557093.chunk.js.gz
hass_frontend/08b70024d3efa1557093.chunk.js.map
hass_frontend/08f1d8015418fef09785.chunk.js
hass_frontend/08f1d8015418fef09785.chunk.js.gz
hass_frontend/08f1d8015418fef09785.chunk.js.map
hass_frontend/0bb5d11e74bcd83e8fdf.chunk.js
hass_frontend/0bb5d11e74bcd83e8fdf.chunk.js.gz
hass_frontend/0bb5d11e74bcd83e8fdf.chunk.js.map
hass_frontend/0d862dbae8095e82c2ed.chunk.js
hass_frontend/0d862dbae8095e82c2ed.chunk.js.gz
hass_frontend/0d862dbae8095e82c2ed.chunk.js.map
hass_frontend/0f332e160ee7aff6c21c.chunk.js
hass_frontend/0f332e160ee7aff6c21c.chunk.js.gz
hass_frontend/0f332e160ee7aff6c21c.chunk.js.map
hass_frontend/11fecc04868ee6c6ff70.chunk.js
hass_frontend/11fecc04868ee6c6ff70.chunk.js.gz
hass_frontend/11fecc04868ee6c6ff70.chunk.js.map
hass_frontend/1396401d4ff090a25c57.chunk.js
hass_frontend/1396401d4ff090a25c57.chunk.js.gz
hass_frontend/1396401d4ff090a25c57.chunk.js.map
hass_frontend/140ffbccdceb970458b1.chunk.js
hass_frontend/140ffbccdceb970458b1.chunk.js.gz
hass_frontend/140ffbccdceb970458b1.chunk.js.map
hass_frontend/16e97bac12a4ec4cf549.chunk.js
hass_frontend/16e97bac12a4ec4cf549.chunk.js.gz
hass_frontend/16e97bac12a4ec4cf549.chunk.js.map
hass_frontend/181aa323a3011c81bfc2.chunk.js
hass_frontend/181aa323a3011c81bfc2.chunk.js.gz
hass_frontend/181aa323a3011c81bfc2.chunk.js.map
